nfnets/__init__.py
nfnets/agc.py
nfnets/base.py
nfnets/sgd_agc.py
nfnets/utils.py
nfnets/models/__init__.py
nfnets/models/resnet.py
nfnets_pytorch-0.1.3.dist-info/LICENSE
nfnets_pytorch-0.1.3.dist-info/METADATA
nfnets_pytorch-0.1.3.dist-info/WHEEL
nfnets_pytorch-0.1.3.dist-info/top_level.txt
nfnets_pytorch-0.1.3.dist-info/RECORD
